gemini_gradio/__init__.py
gemini_gradio-0.0.3.dist-info/METADATA
gemini_gradio-0.0.3.dist-info/WHEEL
gemini_gradio-0.0.3.dist-info/RECORD
