Metadata-Version: 2.4
Name: gemini-gradio
Version: 0.0.3
Summary: A Python package for creating Gradio applications with Google Gemini models
Project-URL: homepage, https://github.com/AK391/gemini-gradio
Project-URL: repository, https://github.com/AK391/gemini-gradio
Author-email: AK <ahsen.khaliq@gmail.com>
License: MIT
Classifier: License :: OSI Approved :: MIT License
Classifier: Operating System :: OS Independent
Classifier: Programming Language :: Python :: 3
Requires-Python: >=3.10
Requires-Dist: google-generativeai
Requires-Dist: gradio-webrtc
Requires-Dist: gradio>=5.9.1
Requires-Dist: numpy
Requires-Dist: twilio
Requires-Dist: websockets
Provides-Extra: dev
Requires-Dist: pytest; extra == 'dev'
